ordeq_requests/__init__.py
ordeq_requests/_version.py
ordeq_requests/py.typed
ordeq_requests/io/__init__.py
ordeq_requests/io/response.py
ordeq_requests-1.0.4.dist-info/licenses/LICENSE
ordeq_requests-1.0.4.dist-info/METADATA
ordeq_requests-1.0.4.dist-info/WHEEL
ordeq_requests-1.0.4.dist-info/top_level.txt
ordeq_requests-1.0.4.dist-info/RECORD
