Metadata-Version: 2.4
Name: ordeq_requests
Version: 1.0.4
Summary: Requests integration for Ordeq
Author: Niels Neerhoff, Simon Brugman
Maintainer: Niels Neerhoff, Simon Brugman
License-Expression: MIT
Requires-Python: >=3.10
License-File: LICENSE
Requires-Dist: ordeq>=1.4.0
Requires-Dist: requests
Dynamic: license-file
